django_forest/__init__.py
django_forest/apps.py
django_forest/urls.py
django_forest/actions/__init__.py
django_forest/actions/urls.py
django_forest/actions/hooks/__init__.py
django_forest/actions/hooks/urls.py
django_forest/actions/hooks/views/__init__.py
django_forest/actions/hooks/views/change.py
django_forest/actions/hooks/views/load.py
django_forest/actions/hooks/views/utils.py
django_forest/actions/views/__init__.py
django_forest/authentication/__init__.py
django_forest/authentication/exception.py
django_forest/authentication/urls.py
django_forest/authentication/utils.py
django_forest/authentication/oidc/__init__.py
django_forest/authentication/oidc/client_manager.py
django_forest/authentication/oidc/configuration_retriever.py
django_forest/authentication/oidc/dynamic_client_registrator.py
django_forest/authentication/views/__init__.py
django_forest/authentication/views/callback.py
django_forest/authentication/views/index.py
django_forest/authentication/views/logout.py
django_forest/middleware/__init__.py
django_forest/middleware/deactivate_count.py
django_forest/middleware/ip_whitelist.py
django_forest/middleware/permissions.py
django_forest/resources/__init__.py
django_forest/resources/urls.py
django_forest/resources/associations/__init__.py
django_forest/resources/associations/urls.py
django_forest/resources/associations/utils/__init__.py
django_forest/resources/associations/utils/association.py
django_forest/resources/associations/views/__init__.py
django_forest/resources/associations/views/count.py
django_forest/resources/associations/views/csv.py
django_forest/resources/associations/views/list.py
django_forest/resources/utils/__init__.py
django_forest/resources/utils/csv.py
django_forest/resources/utils/decorators.py
django_forest/resources/utils/format.py
django_forest/resources/utils/in_search_fields.py
django_forest/resources/utils/json_api_serializer.py
django_forest/resources/utils/query_parameters.py
django_forest/resources/utils/resource.py
django_forestadmin-1.6.11.dist-info/LICENCE
django_forestadmin-1.6.11.dist-info/METADATA
django_forestadmin-1.6.11.dist-info/WHEEL
django_forestadmin-1.6.11.dist-info/top_level.txt
django_forestadmin-1.6.11.dist-info/RECORD
