Metadata-Version: 2.1
Name: django-forestadmin
Version: 1.6.11
Summary: The Django Liana for Forest Admin.
Home-page: https://forestadmin.com/
Author: Guillaume Cisco
Author-email: guillaumec@forestadmin.com
License: GNU General Public License v3 or later (GPLv3+)
Classifier: Environment :: Web Environment
Classifier: Framework :: Django
Classifier: Framework :: Django :: 3.2
Classifier: Framework :: Django :: 4.0
Classifier: Framework :: Django :: 4.1
Classifier: Framework :: Django :: 4.2
Classifier: Intended Audience :: Developers
Classifier: License :: OSI Approved :: GNU General Public License v3 or later (GPLv3+)
Classifier: Operating System :: OS Independent
Classifier: Programming Language :: Python
Classifier: Programming Language :: Python :: 3
Classifier: Programming Language :: Python :: 3 :: Only
Classifier: Programming Language :: Python :: 3.6
Classifier: Programming Language :: Python :: 3.7
Classifier: Programming Language :: Python :: 3.8
Classifier: Programming Language :: Python :: 3.9
Classifier: Programming Language :: Python :: 3.10
Classifier: Programming Language :: Python :: 3.11
Classifier: Topic :: Internet :: WWW/HTTP
Classifier: Topic :: Internet :: WWW/HTTP :: Dynamic Content
Classifier: Topic :: Internet :: WWW/HTTP :: Dynamic Content :: CGI Tools/Libraries
Requires-Python: <3.12,>=3.6
License-File: LICENCE
Requires-Dist: Django <5.0,>=3.2
Requires-Dist: django-cors-headers >=3.7
Requires-Dist: django-ipware <5.0,>=4.0
Requires-Dist: marshmallow-jsonapi <1.0,>=0.24
Requires-Dist: oic <2.0,>=1.3
Requires-Dist: python-dateutil <3.0,>=2.8
Requires-Dist: python-jose <4.0,>=3.3
Requires-Dist: requests <3.0,>=2.25
Requires-Dist: marshmallow >=3.14
Requires-Dist: pandas <=1.5,>=1.1
Requires-Dist: importlib-metadata <4.3,>=4.0 ; python_version < "3.8"
Requires-Dist: backports.zoneinfo <1.0,>=0.2 ; python_version < "3.9"
